Metadata-Version: 1.0
Name: mediawiki-parser
Version: 0.3.1
Summary: A parser for the MediaWiki syntax, based on Pijnu.
Home-page: https://github.com/peter17/mediawiki-parser
Author: Erik Rose, Peter Potrowl
Author-email: grinch@grinchcentral.com, peter.potrowl@gmail.com
License: GPL v3
Keywords: MediaWiki,parser,syntax
Platform: UNKNOWN
